pvplot/__init__.py
pvplot/__main__.py
pvplot/cad_epics.py
pvplot/cad_pvaccess.py
pvplot/helptxt.py
pvplot/pvplot.py
pvplot-1.6.4.dist-info/METADATA
pvplot-1.6.4.dist-info/WHEEL
pvplot-1.6.4.dist-info/licenses/LICENSE
pvplot-1.6.4.dist-info/RECORD
