Metadata-Version: 2.4
Name: pvplot
Version: 1.6.4
Summary: Plotting tool for EPICS PVs, ADO and LITE parameters
Project-URL: Homepage, https://github.com/ASukhanov/pvplot
Project-URL: Bug Tracker, https://github.com/ASukhanov/pvplot/issues
Author-email: Andrei Sukhanov <cyxandr@gmail.com>
License-File: LICENSE
Classifier: License :: OSI Approved :: MIT License
Classifier: Operating System :: OS Independent
Classifier: Programming Language :: Python :: 3
Requires-Python: >=3.7
Requires-Dist: liteaccess
